setup.py
A_Bit_Racey/A_Bit_Racey.py
A_Bit_Racey/__init__.py
A_Bit_Racey.egg-info/PKG-INFO
A_Bit_Racey.egg-info/SOURCES.txt
A_Bit_Racey.egg-info/dependency_links.txt
A_Bit_Racey.egg-info/top_level.txt