Metadata-Version: 1.0
Name: A-Bit-Racey
Version: 1.0.0
Summary: a Python game to play. Uses pygame.
Home-page: UNKNOWN
Author: UNKNOWN
Author-email: UNKNOWN
License: UNKNOWN
Platform: UNKNOWN
